{
  "data_asset_type": null,
  "expectation_suite_name": "default",
  "expectations": [
    {
      "expectation_type": "expect_column_to_exist",
      "kwargs": {
        "column": "Date"
      },
      "meta": {}
    },
    {
      "expectation_type": "expect_column_values_to_not_be_null",
      "kwargs": {
        "column": "region"
      },
      "meta": {}
    },
    {
      "expectation_type": "expect_column_values_to_be_of_type",
      "kwargs": {
        "column": "region",
        "type_": "str"
      },
      "meta": {}
    },
    {
      "expectation_type": "expect_column_values_to_match_strftime_format",
      "kwargs": {
        "column": "Date",
        "strftime_format": "%Y-%m-%d"
      },
      "meta": {}
    },
    {
      "expectation_type": "expect_column_values_to_be_between",
      "kwargs": {
        "column": "AveragePrice",
        "max_value": 3.0,
        "min_value": 0.5,
        "mostly": 0.99
      },
      "meta": {}
    },
    {
      "expectation_type": "expect_column_distinct_values_to_be_in_set",
      "kwargs": {
        "column": "type",
        "value_set": [
          "conventional",
          "organic"
        ]
      },
      "meta": {}
    }
  ],
  "ge_cloud_id": null,
  "meta": {
    "great_expectations_version": "0.18.11"
  }
}